{
  "Routes": [
    {
      "DownstreamPathTemplate": "/auth/{everything}",
      "DownstreamScheme": "http",
      "DownstreamHostAndPorts": [ { "Host": "localhost", "Port": 5277 } ],
      "UpstreamPathTemplate": "/auth/{everything}",
      "UpstreamHttpMethod": [ "Get", "Post", "Put", "Delete" ],
      "SwaggerKey": "auth"
    },
    {
      "DownstreamPathTemplate": "/otp/{everything}",
      "DownstreamScheme": "http",
      "DownstreamHostAndPorts": [ { "Host": "localhost", "Port": 5277 } ],
      "UpstreamPathTemplate": "/otp/{everything}",
      "UpstreamHttpMethod": [ "Get", "Post", "Put", "Delete" ],
      "SwaggerKey": "auth"
    },
    {
      "DownstreamPathTemplate": "/notes/{everything}",
      "DownstreamScheme": "http",
      "DownstreamHostAndPorts": [ { "Host": "localhost", "Port": 5272 } ],
      "UpstreamPathTemplate": "/notes/{everything}",
      "UpstreamHttpMethod": [ "Get", "Post", "Put", "Delete" ],
      "SwaggerKey": "notes"
    }
  ],
  "SwaggerEndPoints": [
    {
      "Key": "auth",
      "Config": [ { "Name": "Auth API", "Version": "v1", "Url": "http://localhost:5277/swagger/v1/swagger.json" } ]
    },
    {
      "Key": "notes",
      "Config": [ { "Name": "Notes API", "Version": "v1", "Url": "http://localhost:5272/swagger/v1/swagger.json" } ]
    }
  ]
}